[
{
    "fields": {
        "variables": [], 
        "platforms": [
            "ISS"
        ], 
        "start_time": "2014-05-30T00:00:00+00:00", 
        "end_time": "2014-07-30T00:00:00+00:00", 
        "name": "30min_winds", 
        "project": "DEEPWAVE"
    }, 
    "model": "ncharts.dataset",
    "pk": 7
},
{
    "fields": {
        "directory": "/scr/isf_apg/projects/deepwave/iss/ds/prof449/std/winds_30", 
        "filenames": "prof449.%Y%m%d.winds.30.nc"
    }, 
    "model": "ncharts.filedataset",
    "pk": 7
},
{
    "fields": {
        "variables": [], 
        "platforms": [
            "GV"
        ], 
        "start_time": "2014-07-01T04:00:00+00:00", 
        "end_time": "2014-07-01T14:00:00+00:00", 
        "name": "GV-1sec", 
        "project": "DEEPWAVE"
    }, 
    "model": "ncharts.dataset",
    "pk": 8
},
{
    "fields": {
        "directory": "/scr/tmp/maclean/DEEPWAVE/GV/netcdf",
        "filenames": "DEEPWAVE_%Y%m%d_rf14.nc"
    }, 
    "model": "ncharts.filedataset",
    "pk": 8
}
]
